tab_manager/__init__.py
tab_manager/cli/__init__.py
tab_manager/dependencies.py
tab_manager/exc.py
tab_manager/logger.py
tab_manager/main.py
tab_manager/schema.py
tab_manager/state.py
tab_manager/utils.py
tab_manager/ws.py
tab_manager-0.1.5.dist-info/METADATA
tab_manager-0.1.5.dist-info/WHEEL
tab_manager-0.1.5.dist-info/entry_points.txt
tab_manager-0.1.5.dist-info/RECORD
